PrettyPrint/__init__.py
PrettyPrint/ansi.py
PrettyPrint/format.py
PrettyPrint/output.py
PrettyPrint/figures/ProgressBar.py
PrettyPrint/figures/RunningIndicator.py
PrettyPrint/figures/Separator.py
PrettyPrint/figures/Table.py
PrettyPrint/figures/__init__.py
PrettyPrintout-1.0.4.dist-info/LICENSE
PrettyPrintout-1.0.4.dist-info/METADATA
PrettyPrintout-1.0.4.dist-info/WHEEL
PrettyPrintout-1.0.4.dist-info/top_level.txt
PrettyPrintout-1.0.4.dist-info/RECORD
