Metadata-Version: 2.1
Name: PrettyPrintout
Version: 1.0.4
Summary: A simple package that contains a set of useful printing options
Author: Lorenz Kuhn
Author-email: <lorenz.achim.kuhn@gmail.com>
Keywords: python,first package,console formatting,output,logging,printing
Classifier: Development Status :: 4 - Beta
Classifier: Intended Audience :: Education
Classifier: Programming Language :: Python :: 2
Classifier: Programming Language :: Python :: 3
Classifier: Operating System :: MacOS :: MacOS X
Classifier: Operating System :: Microsoft :: Windows
License-File: LICENSE
